<edu.ucsc.cross.jheq.core.feature.ContentDefinition>
  <taskInfo>
    <functionCallLabel>edu.ucsc.cross.jheq.core.app.JavaHyEQTaskInfo_1569772164523</functionCallLabel>
  </taskInfo>
  <globalVariableGenerator>
    <entry>
      <string></string>
      <string></string>
    </entry>
  </globalVariableGenerator>
  <systemDefiners>
    <entry>
      <string>system1</string>
      <edu.ucsc.cross.jheq.core.feature.SystemDefinition>
        <taskInfo/>
        <flowMapClass>F</flowMapClass>
        <jumpMapClass>G</jumpMapClass>
        <flowSetClass>C</flowSetClass>
        <jumpSetClass>D</jumpSetClass>
        <outputClasses>
          <string></string>
        </outputClasses>
        <stateClass>State</stateClass>
        <parameterClasses>
          <string></string>
        </parameterClasses>
        <sharedParameters>
          <string></string>
        </sharedParameters>
        <accessKeys>
          <object/>
        </accessKeys>
      </edu.ucsc.cross.jheq.core.feature.SystemDefinition>
    </entry>
  </systemDefiners>
  <postProcess>
    <string></string>
  </postProcess>
  <splitFiles>true</splitFiles>
</edu.ucsc.cross.jheq.core.feature.ContentDefinition>